{
  "era_code": "era_nt_apostolic",
  "story_index": 30,
  "story_title": "3차 전도 여행: 에베소에서 전함",
  "source_version": "2026-06-11",
  "questions": [
    {
      "type": "fact",
      "display_order": 0,
      "question": "본문에서 먼저 두드러지는 장면은 무엇입니까?",
      "choices": [
        "바울이 에베소의 제자들에게 성령을 물으며 그들은 궁금하고 진지한 얼굴로 대답한다",
        "무리가 아무 일도 없었다고 말하며 흩어졌다",
        "지도자들이 복음 전파를 먼저 명령했다"
      ],
      "answer_index": 0,
      "explanation": "행 19:1 — '아볼로가 고린도에 있을 때에 바울이 윗지방으로 다녀 에베소에 와서 어떤 제자들을 만나'"
    },
    {
      "type": "attitude",
      "display_order": 1,
      "question": "이어지는 장면에서 중심 인물은 어떻게 행동합니까?",
      "choices": [
        "바울이 안수하자 그들이 성령을 받고 말하며 주변 사람들은 놀라움과 경외심으로 바라본다",
        "두려워하며 사명을 포기했다",
        "사람들 앞에서 아무 일도 없다고 말했다"
      ],
      "answer_index": 0,
      "explanation": "행 19:1 — '아볼로가 고린도에 있을 때에 바울이 윗지방으로 다녀 에베소에 와서 어떤 제자들을 만나'"
    },
    {
      "type": "story_context",
      "display_order": 2,
      "question": "이 사건의 끝부분에서 이어진 일은 무엇입니까?",
      "choices": [
        "마술 책들이 사람들 앞에서 불태워지고 회개한 이들의 얼굴에는 두려움과 해방감이 함께 드러난다",
        "사람들이 서로 책임을 미루며 떠났다",
        "중심 인물이 아무 설명 없이 숨었다"
      ],
      "answer_index": 0,
      "explanation": "행 19:20 — '이와 같이 주의 말씀이 힘이 있어 흥왕하여 세력을 얻으니라'"
    }
  ]
}
