{
  "era_code": "era_monarchy",
  "story_index": 15,
  "story_title": "솔로몬: 이방의 경탄부터 타락까지",
  "source_version": "2026-05-25",
  "questions": [
    {
      "type": "fact",
      "display_order": 0,
      "question": "솔로몬의 지혜를 시험하러 찾아온 왕은 누구입니까?",
      "choices": [
        "스바 여왕",
        "두로 왕 히람",
        "애굽의 바로"
      ],
      "answer_index": 0,
      "explanation": "왕상 10:1 — '스바 여왕이 ... 어려운 문제로 시험코자 하여 예루살렘에 이르니'"
    },
    {
      "type": "attitude",
      "display_order": 1,
      "question": "솔로몬의 마음이 여호와에게서 떠나게 된 원인은 무엇입니까?",
      "choices": [
        "이방 아내들이 그의 마음을 돌이켰다",
        "전쟁의 패배에 낙심하였다",
        "선지자들이 그를 떠나갔다"
      ],
      "answer_index": 0,
      "explanation": "왕상 11:4 — '그의 아내들이 그의 마음을 돌려 다른 신들을 따르게 하였으므로'"
    },
    {
      "type": "story_context",
      "display_order": 2,
      "question": "「솔로몬: 이방의 경탄부터 타락까지」에서 실제로 일어난 일은 무엇입니까?",
      "choices": [
        "솔로몬의 지혜와 영화는 이방을 놀라게 했지만, 말년의 타락은 왕국의 균열을 예고했다.",
        "성전 소동으로 바울이 붙잡히며 ‘로마까지’의 여정이 시작된다.",
        "나팔이 울리며 경고가 반복되고 회개의 촉구가 이어진다."
      ],
      "answer_index": 0,
      "explanation": "왕상 10:1 — '스바 여왕이 여호와의 이름으로 말미암은 솔로몬의 명예를 듣고 와서 어려운 문제로 저를 시험코자 하여'"
    }
  ]
}
