{
  "era_code": "era_nt_consummation",
  "story_index": 3,
  "story_title": "어린양과 봉인된 두루마리",
  "source_version": "2026-06-12",
  "questions": [
    {
      "type": "fact",
      "display_order": 0,
      "question": "요한이 오른손에서 본 두루마리는 어떤 상태였습니까?",
      "choices": [
        "일곱 인으로 봉해졌다",
        "이미 불에 탔다",
        "빈 종이였다"
      ],
      "answer_index": 0,
      "explanation": "계 5:1 — '일곱 인으로 봉하였더라'"
    },
    {
      "type": "attitude",
      "display_order": 1,
      "question": "두루마리를 펴기에 합당한 분으로 나타난 이는 누구입니까?",
      "choices": [
        "죽임 당한 어린양",
        "로마 황제",
        "힘센 천사"
      ],
      "answer_index": 0,
      "explanation": "계 5:6 — '어린 양이 섰는데 일찍 죽임을 당한 것 같더라'"
    },
    {
      "type": "story_context",
      "display_order": 2,
      "question": "하늘의 존재들이 어린양께 드린 찬양의 이유는 무엇입니까?",
      "choices": [
        "피로 사람들을 사셨기 때문",
        "큰 도시를 세웠기 때문",
        "전쟁 무기를 만들었기 때문"
      ],
      "answer_index": 0,
      "explanation": "계 5:9 — '각 족속과 방언과 백성과 나라 가운데서 사람들을 피로 사서'"
    }
  ]
}
