{
  "era_code": "era_nt_post_apostolic",
  "story_index": 1,
  "story_title": "시험 속에서 말씀을 행하는 믿음",
  "source_version": "2026-06-12",
  "questions": [
    {
      "type": "fact",
      "display_order": 0,
      "question": "야고보가 흩어진 성도들에게 강조한 태도는 무엇입니까?",
      "choices": [
        "말씀을 듣고 행하는 믿음",
        "성전 제사 절차 암기",
        "로마 법정 승소 전략"
      ],
      "answer_index": 0,
      "explanation": "약 1:22 — '말씀을 행하는 자가 되고'"
    },
    {
      "type": "attitude",
      "display_order": 1,
      "question": "참된 경건은 누구를 돌보는 모습으로 드러납니까?",
      "choices": [
        "고아와 과부를 돌보는 모습",
        "부자에게 좋은 자리를 주는 모습",
        "친한 사람만 섬기는 모습"
      ],
      "answer_index": 0,
      "explanation": "약 1:27 — '고아와 과부를 그 환난중에 돌아보고'"
    },
    {
      "type": "story_context",
      "display_order": 2,
      "question": "행함이 없는 믿음에 대해 야고보가 든 비유는 무엇입니까?",
      "choices": [
        "영혼 없는 몸처럼 죽은 것이다",
        "비 없는 구름처럼 떠간다",
        "기름 없는 등잔처럼 잠든다"
      ],
      "answer_index": 0,
      "explanation": "약 2:26 — '행함이 없는 믿음은 죽은 것이니라'"
    }
  ]
}
