{
  "era_code": "era_monarchy",
  "story_index": 12,
  "story_title": "다윗 언약: 집을 세우리라",
  "source_version": "2026-04-24",
  "questions": [
    {
      "type": "fact",
      "display_order": 0,
      "question": "하나님의 언약을 다윗에게 전달한 선지자는 누구입니까?",
      "choices": [
        "나단",
        "엘리야",
        "사무엘"
      ],
      "answer_index": 0,
      "explanation": "삼하 7:4,17 — '나단이 이 모든 말씀과 이 모든 묵시대로 다윗에게 고하니라'"
    },
    {
      "type": "attitude",
      "display_order": 1,
      "question": "하나님은 다윗의 아들이 지을 것이라고 약속하신 것은 무엇입니까?",
      "choices": [
        "하나님의 이름을 위한 집",
        "이스라엘의 큰 성전",
        "다윗 왕의 궁궐"
      ],
      "answer_index": 0,
      "explanation": "삼하 7:13 — '저는 내 이름을 위하여 집을 건축할 것이요'"
    },
    {
      "type": "bible_context",
      "display_order": 2,
      "question": "다윗 언약이 기록된 성경 책은 어디입니까?",
      "choices": [
        "사무엘하",
        "사무엘상",
        "열왕기상"
      ],
      "answer_index": 0,
      "explanation": "삼하 7:1-17에 다윗 언약이 기록됨"
    }
  ]
}
