{
  "era_code": "era_nt_apostolic",
  "story_index": 42,
  "story_title": "아그립바 왕 앞 변론",
  "source_version": "2026-06-19",
  "questions": [
    {
      "type": "fact",
      "display_order": 0,
      "question": "바울은 아그립바 앞에서 어느 길의 만남을 증언했습니까?",
      "choices": [
        "다메섹 길",
        "엠마오 길",
        "여리고 길"
      ],
      "answer_index": 0,
      "explanation": "행 26:12 — '다메섹으로 갔나이다'"
    },
    {
      "type": "attitude",
      "display_order": 1,
      "question": "예수님은 사람들을 어둠에서 어디로 돌리게 하셨습니까?",
      "choices": [
        "빛",
        "감옥",
        "광야"
      ],
      "answer_index": 0,
      "explanation": "행 26:18 — '어두움에서 빛으로'"
    },
    {
      "type": "story_context",
      "display_order": 2,
      "question": "아그립바와 베스도는 바울이 상소하지 않았다면 어떻게 될 수 있었다고 말했습니까?",
      "choices": [
        "석방될 수 있었다",
        "왕이 될 수 있었다",
        "성전장이 될 수 있었다"
      ],
      "answer_index": 0,
      "explanation": "행 26:32 — '가이사에게 호소하지 아니하였더면 놓을 수 있을 뻔하였다'"
    }
  ]
}
